autopasscrack/__init__.py
autopasscrack/auto_brute.py
autopasscrack/cli.py
autopasscrack-0.1.1.dist-info/licenses/LICENSE
autopasscrack-0.1.1.dist-info/METADATA
autopasscrack-0.1.1.dist-info/WHEEL
autopasscrack-0.1.1.dist-info/entry_points.txt
autopasscrack-0.1.1.dist-info/top_level.txt
autopasscrack-0.1.1.dist-info/RECORD
