Metadata-Version: 2.4
Name: autopasscrack
Version: 0.1.1
Summary: Auto brute force web login forms with password list
Author: Your Name
Requires-Python: >=3.7
License-File: LICENSE
Requires-Dist: selenium
Dynamic: author
Dynamic: license-file
Dynamic: requires-dist
Dynamic: requires-python
Dynamic: summary
